Workbook

Sheet Dashboard

Sheet Historical Financials
A1: Metric | B1: 2021 | C1: 2022 | D1: 2023 | E1: 2024 | F1: 2025
A2: Revenue | B2: 365817 | C2: 394328 | D2: 383285 | E2: 391035 | F2: 416161
A3: Gross Profit | B3: 152836 | C3: 170782 | D3: 169148 | E3: 180683 | F3: 195201
A4: Operating Income | B4: 108949 | C4: 119437 | D4: 114301 | E4: 123216 | F4: 133050
A5: Pre-Tax Income | B5: 109207 | C5: 119103 | D5: 113736 | E5: 123485 | F5: 132729
A6: Income Tax Expense | B6: 14527 | C6: 19300 | D6: 16741 | E6: 29749 | F6: 20719
A7: Net Income | B7: 94068 | C7: 99803 | D7: 96995 | E7: 93736 | F7: 112010
A8: Total Debt | B8: 124719 | C8: 120069 | D8: 111088 | E8: 106629 | F8: 98657
A9: CapEx | B9: 11085 | C9: 10708 | D9: 10959 | E9: 9447 | F9: 12715
A10: Depreciation & Amortization | B10: 11284 | C10: 11104 | D10: 11519 | E10: 11445 | F10: 11698
A11: Shares Outstanding | B11: 16426786 | C11: 15943.425 | D11: 15550.061 | E11: 15116.786 | F11: 14773.26
A12: Cash & Equivalents | B12: 34390 | C12: 23646 | D12: 29965 | E12: 29943 | F12: 35934
A15: Metric | B15: 2021 | C15: 2022 | D15: 2023 | E15: 2024 | F15: 2025
A16: Revenue Growth % | B16: N/A | C16: =(C2/B2)-1 -> 0.077937876 | D16: =(D2/C2)-1 -> -0.028004605 | E16: =(E2/D2)-1 -> 0.020219941 | F16: =(F2/E2)-1 -> 0.064255118
A17: Gross Margin % | B17: =B3/B2 -> 0.4177936 | C17: =C3/C2 -> 0.43309631 | D17: =D3/D2 -> 0.4413113 | E17: =E3/E2 -> 0.4620635 | F17: =F3/F2 -> 0.46905164
A18: Operating Margin % | B18: =B4/B2 -> 0.29782378 | C18: =C4/C2 -> 0.30288744 | D18: =D4/D2 -> 0.29821412 | E18: =E4/E2 -> 0.31510223 | F18: =F4/F2 -> 0.319708
A19: Net Margin % | B19: =B7/B2 -> 0.25714497 | C19: =C7/C2 -> 0.25309641 | D19: =D7/D2 -> 0.25306234 | E19: =E7/E2 -> 0.23971256 | F19: =F7/F2 -> 0.26915064
A20: Tax Rate % | B20: =B6/B5 -> 0.13302261 | C20: =C6/C5 -> 0.16204462 | D20: =D6/D5 -> 0.14719174 | E20: =E6/E5 -> 0.24091185 | F20: =F6/F5 -> 0.15610002

Sheet Assumptions
A1: Metric | B1: 2021 | C1: 2022 | D1: 2023 | E1: 2024 | F1: 2025 | G1: 2026E | H1: 2027E | I1: 2028E | J1: 2029E | K1: 2030E
A2: Revenue Growth | C2: ='Historical Financials'!C16 -> 0.077937876 | D2: ='Historical Financials'!D16 -> -0.028004605 | E2: ='Historical Financials'!E16 -> 0.020219941 | F2: ='Historical Financials'!F16 -> 0.064255118 | G2: 0.05 | H2: 0.045 | I2: 0.04 | J2: 0.035 | K2: 0.03
A3: Gross Margin | B3: ='Historical Financials'!B17 -> 0.4177936 | C3: ='Historical Financials'!C17 -> 0.43309631 | D3: ='Historical Financials'!D17 -> 0.4413113 | E3: ='Historical Financials'!E17 -> 0.4620635 | F3: ='Historical Financials'!F17 -> 0.46905164 | G3: 0.47 | H3: 0.47 | I3: 0.47 | J3: 0.47 | K3: 0.47
A4: Operating Margin | B4: ='Historical Financials'!B18 -> 0.29782378 | C4: ='Historical Financials'!C18 -> 0.30288744 | D4: ='Historical Financials'!D18 -> 0.29821412 | E4: ='Historical Financials'!E18 -> 0.31510223 | F4: ='Historical Financials'!F18 -> 0.319708 | G4: 0.32 | H4: ='Historical Financials'!F18 -> 0.319708 | I4: ='Historical Financials'!F18 -> 0.319708 | J4: ='Historical Financials'!F18 -> 0.319708 | K4: ='Historical Financials'!F18 -> 0.319708
A5: Tax Rate | B5: ='Historical Financials'!B20 -> 0.13302261 | C5: ='Historical Financials'!C20 -> 0.16204462 | D5: ='Historical Financials'!D20 -> 0.14719174 | E5: ='Historical Financials'!E20 -> 0.24091185 | F5: ='Historical Financials'!F20 -> 0.15610002 | G5: ='Historical Financials'!F20 -> 0.15610002 | H5: ='Historical Financials'!F20 -> 0.15610002 | I5: ='Historical Financials'!F20 -> 0.15610002 | J5: ='Historical Financials'!F20 -> 0.15610002 | K5: ='Historical Financials'!F20 -> 0.15610002
A6: CapEx % of Revenue | B6: ='Historical Financials'!B9/'Historical Financials'!B2 -> 0.030302036 | C6: ='Historical Financials'!C9/'Historical Financials'!C2 -> 0.027155059 | D6: ='Historical Financials'!D9/'Historical Financials'!D2 -> 0.028592301 | E6: ='Historical Financials'!E9/'Historical Financials'!E2 -> 0.024158963 | F6: ='Historical Financials'!F9/'Historical Financials'!F2 -> 0.030553079 | G6: ='Historical Financials'!F9/'Historical Financials'!F2 -> 0.030553079 | H6: ='Historical Financials'!F9/'Historical Financials'!F2 -> 0.030553079 | I6: ='Historical Financials'!F9/'Historical Financials'!F2 -> 0.030553079 | J6: ='Historical Financials'!F9/'Historical Financials'!F2 -> 0.030553079 | K6: ='Historical Financials'!F9/'Historical Financials'!F2 -> 0.030553079
A7: D&A % of Revenue | B7: ='Historical Financials'!B10/'Historical Financials'!B2 -> 0.030846024 | C7: ='Historical Financials'!C10/'Historical Financials'!C2 -> 0.028159299 | D7: ='Historical Financials'!D10/'Historical Financials'!D2 -> 0.030053355 | E7: ='Historical Financials'!E10/'Historical Financials'!E2 -> 0.02926848 | F7: ='Historical Financials'!F10/'Historical Financials'!F2 -> 0.028109313 | G7: ='Historical Financials'!F10/'Historical Financials'!F2 -> 0.028109313 | H7: ='Historical Financials'!F10/'Historical Financials'!F2 -> 0.028109313 | I7: ='Historical Financials'!F10/'Historical Financials'!F2 -> 0.028109313 | J7: ='Historical Financials'!F10/'Historical Financials'!F2 -> 0.028109313 | K7: ='Historical Financials'!F10/'Historical Financials'!F2 -> 0.028109313
A8: WACC | G8: =(B24*B20)+(B23*B21*(1-B22)) -> 0.087076852 | H8: =(B24*B20)+(B23*B21*(1-B22)) -> 0.087076852 | I8: =(B24*B20)+(B23*B21*(1-B22)) -> 0.087076852 | J8: =(B24*B20)+(B23*B21*(1-B22)) -> 0.087076852 | K8: =(B24*B20)+(B23*B21*(1-B22)) -> 0.087076852
A9: Terminal Growth Rate | K9: 0.025
A10: NWC % of Revenue | F10: 0.01 | G10: 0.01 | H10: 0.01 | I10: 0.01 | J10: 0.01 | K10: 0.01
A16: WACC Inputs | B16: Value
A17: Risk Free Rate | B17: 0.04
A18: Beta | B18: 1.07
A19: Market Risk Premium | B19: 0.045
A20: Cost of Equity | B20: =B17+(B18*B19) -> 0.08815
A21: Cost of Debt | B21: 0.045
A22: Tax Rate | B22: ='Historical Financials'!F20 -> 0.15610002
A23: Debt Weight | B23: ='Historical Financials'!F8/('Historical Financials'!F8+4514000) -> 0.021388323
A24: Equity Weight | B24: =4514000/('Historical Financials'!F8+4514000) -> 0.97861168

Sheet Revenue Forecast
A1: Metric | B1: 2025A | C1: 2026E | D1: 2027E | E1: 2028E | F1: 2029E | G1: 2030E
A2: Revenue | B2: =Table1[[#This Row],[2025]] -> 416161 | C2: =Table7[[#This Row],[2025A]]*(1+C3) -> 436969.05 | D2: =Table7[[#This Row],[2026E]]*(1+D3) -> 456632.66 | E2: =Table7[[#This Row],[2027E]]*(1+E3) -> 474897.96 | F2: =Table7[[#This Row],[2028E]]*(1+F3) -> 491519.39 | G2: =Table7[[#This Row],[2029E]]*(1+G3) -> 506264.97
A3: Revenue Growth % | B3: =Assumptions!F2 -> 0.064255118 | C3: =Assumptions!G2 -> 0.05 | D3: =Assumptions!H2 -> 0.045 | E3: =Assumptions!I2 -> 0.04 | F3: =Assumptions!J2 -> 0.035 | G3: =Assumptions!K2 -> 0.03
A4: Operating Margin % | B4: =Table6[[#This Row],[2025]] -> 0.319708 | C4: =Table6[[#This Row],[2026E]] -> 0.32 | D4: =Table6[[#This Row],[2027E]] -> 0.319708 | E4: =Table6[[#This Row],[2028E]] -> 0.319708 | F4: =Table6[[#This Row],[2029E]] -> 0.319708 | G4: =Table6[[#This Row],[2030E]] -> 0.319708
A5: Tax Rate % | B5: =Table6[[#This Row],[2025]] -> 0.15610002 | C5: =Table6[[#This Row],[2026E]] -> 0.15610002 | D5: =Table6[[#This Row],[2027E]] -> 0.15610002 | E5: =Table6[[#This Row],[2028E]] -> 0.15610002 | F5: =Table6[[#This Row],[2029E]] -> 0.15610002 | G5: =Table6[[#This Row],[2030E]] -> 0.15610002
A6: D&A % of Revenue | B6: =Assumptions!F7 -> 0.028109313 | C6: =Assumptions!G7 -> 0.028109313 | D6: =Assumptions!H7 -> 0.028109313 | E6: =Assumptions!I7 -> 0.028109313 | F6: =Assumptions!J7 -> 0.028109313 | G6: =Assumptions!K7 -> 0.028109313
A7: CapEx % of Revnue | B7: =Assumptions!F6 -> 0.030553079 | C7: =Assumptions!G6 -> 0.030553079 | D7: =Assumptions!H6 -> 0.030553079 | E7: =Assumptions!I6 -> 0.030553079 | F7: =Assumptions!I6 -> 0.030553079 | G7: =Assumptions!K6 -> 0.030553079

Sheet Income Statement Forecast
A1: Metric | B1: 2025A | C1: 2026E | D1: 2027E | E1: 2028E | F1: 2029E | G1: 2030E
A2: Revenue | B2: =Table7[[#This Row],[2025A]] -> 416161 | C2: =Table7[[#This Row],[2026E]] -> 436969.05 | D2: =Table7[[#This Row],[2027E]] -> 456632.66 | E2: =Table7[[#This Row],[2028E]] -> 474897.96 | F2: =Table7[[#This Row],[2029E]] -> 491519.39 | G2: =Table7[[#This Row],[2030E]] -> 506264.97
A3: COGS | B3: =B2*(1-Table6[[#This Row],[2025]]) -> 220960 | C3: =C2*(1-Table6[[#This Row],[2026E]]) -> 231593.6 | D3: =D2*(1-Table6[[#This Row],[2027E]]) -> 242015.31 | E3: =E2*(1-Table6[[#This Row],[2028E]]) -> 251695.92 | F3: =F2*(1-Table6[[#This Row],[2029E]]) -> 260505.28 | G3: =G2*(1-Table6[[#This Row],[2030E]]) -> 268320.44
A4: Gross Profit | B4: =B2-B3 -> 195201 | C4: =C2-C3 -> 205375.45 | D4: =D2-D3 -> 214617.35 | E4: =E2-E3 -> 223202.04 | F4: =F2-F3 -> 231014.11 | G4: =G2-G3 -> 237944.54
A5: Gross Margin % | B5: =B4/B2 -> 0.46905164 | C5: =C4/C2 -> 0.47 | D5: =D4/D2 -> 0.47 | E5: =E4/E2 -> 0.47 | F5: =F4/F2 -> 0.47 | G5: =G4/G2 -> 0.47
A6: Operating Income | B6: =B2*'Revenue Forecast'!B4 -> 133050 | C6: =C2*'Revenue Forecast'!C4 -> 139830.1 | D6: =D2*'Revenue Forecast'!D4 -> 145989.11 | E6: =E2*'Revenue Forecast'!E4 -> 151828.68 | F6: =F2*'Revenue Forecast'!F4 -> 157142.68 | G6: =G2*'Revenue Forecast'!G4 -> 161856.96
A7: Operating Expenses | B7: =B4-B6 -> 62151 | C7: =C4-C6 -> 65545.357 | D7: =D4-D6 -> 68628.236 | E7: =E4-E6 -> 71373.366 | F7: =F4-F6 -> 73871.434 | G7: =G4-G6 -> 76087.577
A8: Operating Margin % | B8: =B6/B2 -> 0.319708 | C8: =C6/C2 -> 0.32 | D8: =D6/D2 -> 0.319708 | E8: =E6/E2 -> 0.319708 | F8: =F6/F2 -> 0.319708 | G8: =G6/G2 -> 0.319708
A9: Taxes | B9: =B6*Assumptions!F5 -> 20769.108 | C9: =C6*Assumptions!G5 -> 21827.481 | D9: =D6*Assumptions!H5 -> 22788.904 | E9: =E6*Assumptions!I5 -> 23700.46 | F9: =F6*Assumptions!J5 -> 24529.976 | G9: =G6*Assumptions!K5 -> 25265.875
A10: NOPAT | B10: =B6-B9 -> 112280.89 | C10: =C6-C9 -> 118002.61 | D10: =D6-D9 -> 123200.21 | E10: =E6-E9 -> 128128.22 | F10: =F6-F9 -> 132612.7 | G10: =G6-G9 -> 136591.09

Sheet Free Cash Flow
A1: Metric | B1: 2025A | C1: 2026E | D1: 2027E | E1: 2028E | F1: 2029E | G1: 2030E
A2: Revenue | B2: =Table7[[#This Row],[2025A]] -> 416161 | C2: =Table7[[#This Row],[2026E]] -> 436969.05 | D2: =Table7[[#This Row],[2027E]] -> 456632.66 | E2: =Table7[[#This Row],[2028E]] -> 474897.96 | F2: =Table7[[#This Row],[2029E]] -> 491519.39 | G2: =Table7[[#This Row],[2030E]] -> 506264.97
A3: NOPAT | B3: ='Income Statement Forecast'!B10 -> 112280.89 | C3: ='Income Statement Forecast'!C10 -> 118002.61 | D3: ='Income Statement Forecast'!D10 -> 123200.21 | E3: ='Income Statement Forecast'!E10 -> 128128.22 | F3: ='Income Statement Forecast'!F10 -> 132612.7 | G3: ='Income Statement Forecast'!G10 -> 136591.09
A4: D&A | B4: =B2*Assumptions!F7 -> 11698 | C4: =C2*Assumptions!G7 -> 12282.9 | D4: =D2*Assumptions!H7 -> 12835.63 | E4: =E2*Assumptions!I7 -> 13349.056 | F4: =F2*Assumptions!J7 -> 13816.273 | G4: =G2*Assumptions!K7 -> 14230.761
A5: CapEx | B5: =B2*Assumptions!F6 -> 12715 | C5: =C2*Assumptions!G6 -> 13350.75 | D5: =D2*Assumptions!H6 -> 13951.534 | E5: =E2*Assumptions!I6 -> 14509.595 | F5: =F2*Assumptions!J6 -> 15017.431 | G5: =G2*Assumptions!K6 -> 15467.954
A6: NWC | B6: =B2*Assumptions!F10 -> 4161.61 | C6: =C2*Assumptions!G10 -> 4369.6905 | D6: =D2*Assumptions!H10 -> 4566.3266 | E6: =E2*Assumptions!I10 -> 4748.9796 | F6: =F2*Assumptions!J10 -> 4915.1939 | G6: =G2*Assumptions!K10 -> 5062.6497
A7: Change in NWC | B7: 0 | C7: =C6-B6 -> 208.0805 | D7: =D6-C6 -> 196.63607 | E7: =E6-D6 -> 182.65306 | F7: =F6-E6 -> 166.21429 | G7: =G6-F6 -> 147.45582
A8: UFCF | B8: =B3+B4-B5-B7 -> 111263.89 | C8: =C3+C4-C5-C7 -> 116726.68 | D8: =D3+D4-D5-D7 -> 121887.67 | E8: =E3+E4-E5-E7 -> 126785.02 | F8: =F3+F4-F5-F7 -> 131245.33 | G8: =G3+G4-G5-G7 -> 135206.44

Sheet DCF Valuation - Sens. Analysis
A1: Metric | B1: 2026E | C1: 2027E | D1: 2028E | E1: 2029E | F1: 2030E | H1: Metric | I1: Value
A2: UFCF | B2: ='Free Cash Flow'!B8 -> 111263.89 | C2: ='Free Cash Flow'!C8 -> 116726.68 | D2: ='Free Cash Flow'!D8 -> 121887.67 | E2: ='Free Cash Flow'!E8 -> 126785.02 | F2: ='Free Cash Flow'!F8 -> 131245.33 | H2: WACC | I2: =Assumptions!G8 -> 0.087076852 | K2: Apple DCF Sensitivity Analysis (Intrinsic Value per Share)
A3: Discount Factor | B3: =1/(1+$B$9)^1 -> 0.91989816 | C3: =1/(1+$B$9)^2 -> 0.84621263 | D3: =1/(1+$B$9)^3 -> 0.77842945 | E3: =1/(1+$B$9)^4 -> 0.71607582 | F3: =1/(1+$B$9)^5 -> 0.65871683 | H3: Terminal Growth Rate | I3: =Assumptions!K9 -> 0.025 | K3: Terminal Growth Rate / WACC
A4: Present Value | B4: =B2*B3 -> 102351.45 | C4: =C2*C3 -> 98775.595 | D4: =D2*D3 -> 94880.951 | E4: =E2*E3 -> 90787.69 | F4: =F2*F3 -> 86453.509 | H4: Enterprise Value | I4: =SUM(B4:F4)+F6 -> 1900751.5 | K4: =I9 -> 124.4159 | L4: 0.067 | M4: 0.077 | N4: 0.087 | O4: 0.097 | P4: 0.107
A5: Terminal Value | F5: =(F2*(1+$B$10))/($B$9-$B$10) -> 2167095.5 | H5: Cash | I5: ='Historical Financials'!F12 -> 35934 | K5: 0.015 | L5: 154.97537 | M5: 129.04301 | N5: 110.32155 | O5: 96.17257 | P5: 85.104783
A6: PV of Terminal Value | F6: =F5*F3 -> 1427502.3 | H6: Debt | I6: ='Historical Financials'!F8 -> 98657 | K6: 0.02 | L6: 168.99765 | M6: 138.38519 | N6: 116.91712 | O6: 101.03045 | P6: 88.80034
H7: Equity Value | I7: =I4+I5-I6 -> 1838028.5 | K7: 0.025 | L7: 186.35857 | M7: 149.52394 | N7: 124.57649 | O7: 106.56303 | P7: 92.946576
A8: Metric | B8: Value | H8: Shares Outstanding | I8: ='Historical Financials'!F11 -> 14773.26 | K8: 0.03 | L8: 208.41163 | M8: 163.03264 | N8: 133.5796 | O8: 112.92137 | P8: 97.631283
A9: WACC Input | B9: =I2 -> 0.087076852 | H9: Intrinsic Value Per Share | I9: =I7/I8 -> 124.4159 | K9: 0.035 | L9: 237.35627 | M9: 179.75769 | N9: 144.31408 | O9: 120.30525 | P9: 102.96664
A10: Growth Input | B10: =I3 -> 0.025
O11: D
